cccAPI/__init__.py
cccAPI/application.py
cccAPI/client.py
cccAPI/conn.py
cccAPI/custom_groups.py
cccAPI/image_groups.py
cccAPI/network_groups.py
cccAPI/nodes.py
cccAPI/resource_features.py
cccAPI/tasks.py
cccAPI/definitions/Action.json
cccAPI/definitions/ActionParameterObject.json
cccAPI/definitions/ApplicationDescriptionDTO.json
cccAPI/definitions/CustomGroup.json
cccAPI/definitions/FeatureObject.json
cccAPI/definitions/FeaturesDto.json
cccAPI/definitions/Group.json
cccAPI/definitions/ImageGroup.json
cccAPI/definitions/ImageSettings.json
cccAPI/definitions/LoginPasswordDTO.json
cccAPI/definitions/ManagementSettings.json
cccAPI/definitions/MultipleIdentifierDto.json
cccAPI/definitions/NetworkGroup.json
cccAPI/definitions/NetworkSettings.json
cccAPI/definitions/Node.json
cccAPI/definitions/PlatformSettings.json
cccAPI/definitions/__init__.py
cccapi-0.0.14.dist-info/METADATA
cccapi-0.0.14.dist-info/WHEEL
cccapi-0.0.14.dist-info/top_level.txt
cccapi-0.0.14.dist-info/RECORD
