Metadata-Version: 2.4
Name: cccAPI
Version: 0.0.14
Summary: Python API Client for CCC
Home-page: https://github.com/atripathy86/cccAPI
Author: Aalap Tripathy
Author-email: Aalap Tripathy <atripathy.bulk@gmail.com>
License: MIT
Project-URL: Homepage, https://github.com/atripathy86/cccAPI
Project-URL: Documentation, https://github.com/atripathy86/cccAPI
Project-URL: Source, https://github.com/atripathy86/cccAPI
Project-URL: Issues, https://github.com/atripathy86/cccAPI/issues
Keywords: ccc,compute cluster controller,fleet,api,client,hpc
Classifier: Development Status :: 4 - Beta
Classifier: Intended Audience :: Developers
Classifier: License :: OSI Approved :: MIT License
Classifier: Programming Language :: Python :: 3
Classifier: Programming Language :: Python :: 3.8
Classifier: Programming Language :: Python :: 3.9
Classifier: Programming Language :: Python :: 3.10
Classifier: Programming Language :: Python :: 3.11
Classifier: Programming Language :: Python :: 3.12
Requires-Python: >=3.6
Requires-Dist: requests>=2.26.0
Requires-Dist: jsonschema>=4.23.0
Dynamic: author
Dynamic: home-page
Dynamic: requires-python
